mdsite/__init__.py
mdsite/data.py
mdsite/data_test.py
mdsite/testdata/config.toml
mdsite/testdata/conflict/index.md
mdsite/testdata/conflict.md
mdsite/testdata/json.md
mdsite/testdata/nohead.md
mdsite/testdata/nougat/config.json
mdsite/testdata/toml.md
mdsite/testdata/yaml.md
markdown_site_utils-0.2.2.dist-info/LICENSE
markdown_site_utils-0.2.2.dist-info/WHEEL
markdown_site_utils-0.2.2.dist-info/METADATA
markdown_site_utils-0.2.2.dist-info/RECORD
