Metadata-Version: 2.1
Name: markdown-site-utils
Version: 0.2.2
Summary: Some utilities for managing Markdown files with metadata.
Home-page: https://github.com/smulloni/markdown_site_utils
License: MIT
Author: Jacob Smullyan
Author-email: smulloni@smullyan.org
Requires-Python: >=3.11,<4.0
Classifier: License :: OSI Approved :: MIT License
Classifier: Programming Language :: Python :: 3
Classifier: Programming Language :: Python :: 3.11
Requires-Dist: MarkupSafe (>=2.1.2,<3.0.0)
Requires-Dist: PyYAML (>=6.0,<7.0)
Requires-Dist: markdown2 (>=2.4.8,<3.0.0)
Requires-Dist: toml (>=0.10.2,<0.11.0)
Project-URL: Repository, https://github.com/smulloni/markdown_site_utils
